telegrampy/__init__.py
telegrampy/abc.py
telegrampy/chat.py
telegrampy/client.py
telegrampy/errors.py
telegrampy/file.py
telegrampy/http.py
telegrampy/message.py
telegrampy/poll.py
telegrampy/user.py
telegrampy/utils.py
telegrampy/ext/commands/__init__.py
telegrampy/ext/commands/bot.py
telegrampy/ext/commands/cog.py
telegrampy/ext/commands/context.py
telegrampy/ext/commands/converter.py
telegrampy/ext/commands/core.py
telegrampy/ext/commands/errors.py
telegrampy/ext/commands/help.py
telegram.py-0.3.1.dist-info/LICENSE
telegram.py-0.3.1.dist-info/METADATA
telegram.py-0.3.1.dist-info/WHEEL
telegram.py-0.3.1.dist-info/top_level.txt
telegram.py-0.3.1.dist-info/RECORD
