Metadata-Version: 2.1
Name: telegram.py
Version: 0.3.1
Summary: An async API wrapper for Telegram bot API in Python
Home-page: https://github.com/ilovetocode2019/telegram.py
Author: ilovetocode
License: UNKNOWN
Project-URL: Documentation, https://telegrampy.readthedocs.io
Project-URL: Issue tracker, https://github.com/ilovetocode2019/telegram.py/issues
Platform: UNKNOWN
Classifier: Development Status :: 3 - Alpha
Classifier: Programming Language :: Python :: 3.7
Classifier: Programming Language :: Python :: 3.8
Classifier: Programming Language :: Python :: 3.9
Classifier: License :: OSI Approved :: MIT License
Classifier: Intended Audience :: Developers
Classifier: Operating System :: OS Independent
Requires-Python: >=3.7
Provides-Extra: docs
